uchuutools/__init__.py
uchuutools/__version__.py
uchuutools/convert_ascii_ctrees_to_h5.py
uchuutools/convert_ascii_halocat_to_h5.py
uchuutools/ctrees_utils.py
uchuutools/utils.py
uchuutools/converters/__init__.py
uchuutools/converters/convert_ascii_ctrees_to_h5.py
uchuutools/converters/convert_ascii_halocat_to_h5.py
uchuutools/tests/__init__.py
uchuutools/tests/test_tree_conversion.py
uchuutools-0.1.0.dist-info/LICENSE
uchuutools-0.1.0.dist-info/METADATA
uchuutools-0.1.0.dist-info/WHEEL
uchuutools-0.1.0.dist-info/top_level.txt
uchuutools-0.1.0.dist-info/RECORD
